MLCArel/IOtable.py
MLCArel/Kriging.py
MLCArel/LimitState.py
MLCArel/PyMLCA.py
MLCArel/__init__.py
mlcarel-0.2.0.dist-info/licenses/LICENSE
mlcarel-0.2.0.dist-info/METADATA
mlcarel-0.2.0.dist-info/WHEEL
mlcarel-0.2.0.dist-info/top_level.txt
mlcarel-0.2.0.dist-info/RECORD
