Metadata-Version: 2.4
Name: mlcarel
Version: 0.2.0
Summary: Software for Generalized Matrix-based LCA and Reliability Based LCA
Home-page: https://github.com/ShinsukeSakai0321/PyMLCA
Author: Shinsuke Sakai
Author-email: sakaishin0321@gmail.com
License: MIT
Classifier: Programming Language :: Python :: 3
Classifier: License :: OSI Approved :: MIT License
Classifier: Operating System :: OS Independent
Requires-Python: >=3.6
License-File: LICENSE
Requires-Dist: pandas>=2.2.3
Requires-Dist: pyDOE>=0.3.8
Requires-Dist: scikit-learn>=1.6.1
Requires-Dist: LimitState>=0.0.2
Dynamic: author
Dynamic: author-email
Dynamic: classifier
Dynamic: description
Dynamic: description-content-type
Dynamic: home-page
Dynamic: license
Dynamic: license-file
Dynamic: requires-dist
Dynamic: requires-python
Dynamic: summary
